{
 "cells": [
  {
   "cell_type": "code",
   "execution_count": 1,
   "id": "7163a400",
   "metadata": {},
   "outputs": [],
   "source": [
    "def hello():\n",
    "    return f'Hello, world!'"
   ]
  },
  {
   "cell_type": "code",
   "execution_count": 2,
   "id": "9a19a340",
   "metadata": {},
   "outputs": [
    {
     "data": {
      "text/plain": [
       "'Hello, world!'"
      ]
     },
     "execution_count": 2,
     "metadata": {},
     "output_type": "execute_result"
    }
   ],
   "source": [
    "hello()"
   ]
  },
  {
   "cell_type": "code",
   "execution_count": 3,
   "id": "ee879a0a",
   "metadata": {},
   "outputs": [],
   "source": [
    "import dis"
   ]
  },
  {
   "cell_type": "code",
   "execution_count": 4,
   "id": "823c2bc1",
   "metadata": {},
   "outputs": [
    {
     "name": "stdout",
     "output_type": "stream",
     "text": [
      "  2           0 LOAD_CONST               1 ('Hello, world!')\n",
      "              2 RETURN_VALUE\n"
     ]
    }
   ],
   "source": [
    "dis.dis(hello)"
   ]
  },
  {
   "cell_type": "code",
   "execution_count": 5,
   "id": "75698cab",
   "metadata": {},
   "outputs": [
    {
     "data": {
      "text/plain": [
       "['__class__',\n",
       " '__delattr__',\n",
       " '__dir__',\n",
       " '__doc__',\n",
       " '__eq__',\n",
       " '__format__',\n",
       " '__ge__',\n",
       " '__getattribute__',\n",
       " '__gt__',\n",
       " '__hash__',\n",
       " '__init__',\n",
       " '__init_subclass__',\n",
       " '__le__',\n",
       " '__lt__',\n",
       " '__ne__',\n",
       " '__new__',\n",
       " '__reduce__',\n",
       " '__reduce_ex__',\n",
       " '__repr__',\n",
       " '__setattr__',\n",
       " '__sizeof__',\n",
       " '__str__',\n",
       " '__subclasshook__',\n",
       " 'co_argcount',\n",
       " 'co_cellvars',\n",
       " 'co_code',\n",
       " 'co_consts',\n",
       " 'co_filename',\n",
       " 'co_firstlineno',\n",
       " 'co_flags',\n",
       " 'co_freevars',\n",
       " 'co_kwonlyargcount',\n",
       " 'co_lines',\n",
       " 'co_linetable',\n",
       " 'co_lnotab',\n",
       " 'co_name',\n",
       " 'co_names',\n",
       " 'co_nlocals',\n",
       " 'co_posonlyargcount',\n",
       " 'co_stacksize',\n",
       " 'co_varnames',\n",
       " 'replace']"
      ]
     },
     "execution_count": 5,
     "metadata": {},
     "output_type": "execute_result"
    }
   ],
   "source": [
    "dir(hello.__code__)"
   ]
  },
  {
   "cell_type": "code",
   "execution_count": 6,
   "id": "bdbc2dce",
   "metadata": {},
   "outputs": [
    {
     "data": {
      "text/plain": [
       "(None, 'Hello, world!')"
      ]
     },
     "execution_count": 6,
     "metadata": {},
     "output_type": "execute_result"
    }
   ],
   "source": [
    "hello.__code__.co_consts"
   ]
  },
  {
   "cell_type": "code",
   "execution_count": 7,
   "id": "5b9fa39f",
   "metadata": {},
   "outputs": [
    {
     "name": "stdout",
     "output_type": "stream",
     "text": [
      "  2           0 LOAD_CONST               1 ('Hello, world!')\n",
      "              2 RETURN_VALUE\n"
     ]
    }
   ],
   "source": [
    "dis.dis(hello)"
   ]
  },
  {
   "cell_type": "code",
   "execution_count": 8,
   "id": "1bb6929c",
   "metadata": {},
   "outputs": [],
   "source": [
    "def myfunc():\n",
    "    return 5\n"
   ]
  },
  {
   "cell_type": "code",
   "execution_count": 9,
   "id": "2de14eeb",
   "metadata": {},
   "outputs": [
    {
     "name": "stdout",
     "output_type": "stream",
     "text": [
      "  2           0 LOAD_CONST               1 (5)\n",
      "              2 RETURN_VALUE\n"
     ]
    }
   ],
   "source": [
    "dis.dis(myfunc)"
   ]
  },
  {
   "cell_type": "code",
   "execution_count": 10,
   "id": "4d1466a8",
   "metadata": {},
   "outputs": [],
   "source": [
    "def myfunc():\n",
    "    return [10, 20, 30]"
   ]
  },
  {
   "cell_type": "code",
   "execution_count": 11,
   "id": "8469d4a1",
   "metadata": {},
   "outputs": [
    {
     "name": "stdout",
     "output_type": "stream",
     "text": [
      "  2           0 BUILD_LIST               0\n",
      "              2 LOAD_CONST               1 ((10, 20, 30))\n",
      "              4 LIST_EXTEND              1\n",
      "              6 RETURN_VALUE\n"
     ]
    }
   ],
   "source": [
    "dis.dis(myfunc)"
   ]
  },
  {
   "cell_type": "code",
   "execution_count": 12,
   "id": "4de80844",
   "metadata": {},
   "outputs": [
    {
     "data": {
      "text/plain": [
       "(None, (10, 20, 30))"
      ]
     },
     "execution_count": 12,
     "metadata": {},
     "output_type": "execute_result"
    }
   ],
   "source": [
    "myfunc.__code__.co_consts"
   ]
  },
  {
   "cell_type": "code",
   "execution_count": 13,
   "id": "b0a4c229",
   "metadata": {},
   "outputs": [],
   "source": [
    "def myfunc():\n",
    "    return [10, 20]"
   ]
  },
  {
   "cell_type": "code",
   "execution_count": 14,
   "id": "1d834c80",
   "metadata": {},
   "outputs": [
    {
     "name": "stdout",
     "output_type": "stream",
     "text": [
      "  2           0 LOAD_CONST               1 (10)\n",
      "              2 LOAD_CONST               2 (20)\n",
      "              4 BUILD_LIST               2\n",
      "              6 RETURN_VALUE\n"
     ]
    }
   ],
   "source": [
    "dis.dis(myfunc)"
   ]
  },
  {
   "cell_type": "code",
   "execution_count": 15,
   "id": "9d4161f0",
   "metadata": {},
   "outputs": [
    {
     "data": {
      "text/plain": [
       "(None, 10, 20)"
      ]
     },
     "execution_count": 15,
     "metadata": {},
     "output_type": "execute_result"
    }
   ],
   "source": [
    "myfunc.__code__.co_consts"
   ]
  },
  {
   "cell_type": "code",
   "execution_count": 16,
   "id": "d4a4dbbf",
   "metadata": {},
   "outputs": [],
   "source": [
    "def myfunc():\n",
    "    return (10, 20, 30)"
   ]
  },
  {
   "cell_type": "code",
   "execution_count": 17,
   "id": "cec2c0a6",
   "metadata": {},
   "outputs": [
    {
     "name": "stdout",
     "output_type": "stream",
     "text": [
      "  2           0 LOAD_CONST               1 ((10, 20, 30))\n",
      "              2 RETURN_VALUE\n"
     ]
    }
   ],
   "source": [
    "dis.dis(myfunc)"
   ]
  },
  {
   "cell_type": "code",
   "execution_count": 18,
   "id": "a3d54968",
   "metadata": {},
   "outputs": [
    {
     "data": {
      "text/plain": [
       "(None, (10, 20, 30))"
      ]
     },
     "execution_count": 18,
     "metadata": {},
     "output_type": "execute_result"
    }
   ],
   "source": [
    "myfunc.__code__.co_consts"
   ]
  },
  {
   "cell_type": "code",
   "execution_count": 19,
   "id": "9bbeb848",
   "metadata": {},
   "outputs": [],
   "source": [
    "def myfunc():\n",
    "    d = {'a':1, 'b':2, 'c':3}\n",
    "    return d"
   ]
  },
  {
   "cell_type": "code",
   "execution_count": 20,
   "id": "9e47eaee",
   "metadata": {},
   "outputs": [
    {
     "name": "stdout",
     "output_type": "stream",
     "text": [
      "  2           0 LOAD_CONST               1 (1)\n",
      "              2 LOAD_CONST               2 (2)\n",
      "              4 LOAD_CONST               3 (3)\n",
      "              6 LOAD_CONST               4 (('a', 'b', 'c'))\n",
      "              8 BUILD_CONST_KEY_MAP      3\n",
      "             10 STORE_FAST               0 (d)\n",
      "\n",
      "  3          12 LOAD_FAST                0 (d)\n",
      "             14 RETURN_VALUE\n"
     ]
    }
   ],
   "source": [
    "dis.dis(myfunc)"
   ]
  },
  {
   "cell_type": "code",
   "execution_count": 21,
   "id": "fe37d179",
   "metadata": {},
   "outputs": [],
   "source": [
    "def myfunc():\n",
    "    return {'a':1, 'b':2, 'c':3}\n"
   ]
  },
  {
   "cell_type": "code",
   "execution_count": 22,
   "id": "7baca2f9",
   "metadata": {},
   "outputs": [
    {
     "name": "stdout",
     "output_type": "stream",
     "text": [
      "  2           0 LOAD_CONST               1 (1)\n",
      "              2 LOAD_CONST               2 (2)\n",
      "              4 LOAD_CONST               3 (3)\n",
      "              6 LOAD_CONST               4 (('a', 'b', 'c'))\n",
      "              8 BUILD_CONST_KEY_MAP      3\n",
      "             10 RETURN_VALUE\n"
     ]
    }
   ],
   "source": [
    "dis.dis(myfunc)"
   ]
  },
  {
   "cell_type": "code",
   "execution_count": 23,
   "id": "b4ca64c3",
   "metadata": {},
   "outputs": [],
   "source": [
    "def myfunc():\n",
    "    d = {'a':1, 'b':2, 'c':3}\n",
    "    return d"
   ]
  },
  {
   "cell_type": "code",
   "execution_count": 24,
   "id": "bcd6e7cb",
   "metadata": {},
   "outputs": [
    {
     "name": "stdout",
     "output_type": "stream",
     "text": [
      "  2           0 LOAD_CONST               1 (1)\n",
      "              2 LOAD_CONST               2 (2)\n",
      "              4 LOAD_CONST               3 (3)\n",
      "              6 LOAD_CONST               4 (('a', 'b', 'c'))\n",
      "              8 BUILD_CONST_KEY_MAP      3\n",
      "             10 STORE_FAST               0 (d)\n",
      "\n",
      "  3          12 LOAD_FAST                0 (d)\n",
      "             14 RETURN_VALUE\n"
     ]
    }
   ],
   "source": [
    "dis.dis(myfunc)"
   ]
  },
  {
   "cell_type": "code",
   "execution_count": 25,
   "id": "71428ec8",
   "metadata": {},
   "outputs": [
    {
     "data": {
      "text/plain": [
       "('d',)"
      ]
     },
     "execution_count": 25,
     "metadata": {},
     "output_type": "execute_result"
    }
   ],
   "source": [
    "myfunc.__code__.co_varnames"
   ]
  },
  {
   "cell_type": "code",
   "execution_count": 26,
   "id": "795f7b02",
   "metadata": {},
   "outputs": [],
   "source": [
    "def myfunc():\n",
    "    global d    # when you see an assignment to d, don't make d into a local variable; store in the global d\n",
    "    d = {'a':1, 'b':2, 'c':3}\n",
    "    return d"
   ]
  },
  {
   "cell_type": "code",
   "execution_count": 27,
   "id": "e6c67363",
   "metadata": {},
   "outputs": [
    {
     "name": "stdout",
     "output_type": "stream",
     "text": [
      "  3           0 LOAD_CONST               1 (1)\n",
      "              2 LOAD_CONST               2 (2)\n",
      "              4 LOAD_CONST               3 (3)\n",
      "              6 LOAD_CONST               4 (('a', 'b', 'c'))\n",
      "              8 BUILD_CONST_KEY_MAP      3\n",
      "             10 STORE_GLOBAL             0 (d)\n",
      "\n",
      "  4          12 LOAD_GLOBAL              0 (d)\n",
      "             14 RETURN_VALUE\n"
     ]
    }
   ],
   "source": [
    "dis.dis(myfunc)"
   ]
  },
  {
   "cell_type": "code",
   "execution_count": 28,
   "id": "1781ab55",
   "metadata": {},
   "outputs": [
    {
     "data": {
      "text/plain": [
       "()"
      ]
     },
     "execution_count": 28,
     "metadata": {},
     "output_type": "execute_result"
    }
   ],
   "source": [
    "myfunc.__code__.co_varnames"
   ]
  },
  {
   "cell_type": "code",
   "execution_count": 29,
   "id": "19d52a47",
   "metadata": {},
   "outputs": [],
   "source": [
    "def myfunc():\n",
    "    return {10, 20, 30}"
   ]
  },
  {
   "cell_type": "code",
   "execution_count": 30,
   "id": "386926ea",
   "metadata": {},
   "outputs": [
    {
     "name": "stdout",
     "output_type": "stream",
     "text": [
      "  2           0 BUILD_SET                0\n",
      "              2 LOAD_CONST               1 (frozenset({10, 20, 30}))\n",
      "              4 SET_UPDATE               1\n",
      "              6 RETURN_VALUE\n"
     ]
    }
   ],
   "source": [
    "dis.dis(myfunc)"
   ]
  },
  {
   "cell_type": "code",
   "execution_count": 31,
   "id": "eb0c7d9f",
   "metadata": {},
   "outputs": [
    {
     "data": {
      "text/plain": [
       "(None, frozenset({10, 20, 30}))"
      ]
     },
     "execution_count": 31,
     "metadata": {},
     "output_type": "execute_result"
    }
   ],
   "source": [
    "myfunc.__code__.co_consts"
   ]
  },
  {
   "cell_type": "code",
   "execution_count": null,
   "id": "5fd51244",
   "metadata": {},
   "outputs": [],
   "source": []
  }
 ],
 "metadata": {
  "kernelspec": {
   "display_name": "Python 3 (ipykernel)",
   "language": "python",
   "name": "python3"
  },
  "language_info": {
   "codemirror_mode": {
    "name": "ipython",
    "version": 3
   },
   "file_extension": ".py",
   "mimetype": "text/x-python",
   "name": "python",
   "nbconvert_exporter": "python",
   "pygments_lexer": "ipython3",
   "version": "3.10.5"
  }
 },
 "nbformat": 4,
 "nbformat_minor": 5
}
